lj_api_client/__init__.py
lj_api_client/cli/__init__.py
lj_api_client/cli/app.py
lj_api_client/cli/card.py
lj_api_client/cli/config.py
lj_api_client/cli/utils.py
lj_api_client/cli/workspace.py
lj_api_client/client.py
lj_api_client/exceptions.py
lj_api_client/resources.py
lj_api_client/schemas.py
lj_api_client/utils.py
lj_api_client-0.1.1.dist-info/entry_points.txt
lj_api_client-0.1.1.dist-info/WHEEL
lj_api_client-0.1.1.dist-info/METADATA
lj_api_client-0.1.1.dist-info/RECORD
