Metadata-Version: 2.1
Name: lj-api-client
Version: 0.1.1
Summary: API client for Livejourney App
Author: Livejourney
Author-email: api@livejourney.com
Requires-Python: >=3.9,<4.0
Classifier: Programming Language :: Python :: 3
Classifier: Programming Language :: Python :: 3.9
Classifier: Programming Language :: Python :: 3.10
Requires-Dist: pydantic (>=1.10.2,<2.0.0)
Requires-Dist: requests (>=2.28.1,<3.0.0)
Requires-Dist: typer[all] (>=0.6.1,<0.7.0)
